sigconfluence/__init__.py
sigconfluence/client.py
sigconfluence/contents.py
sigconfluence/exceptions.py
sigconfluence/issues.py
sigconfluence/permissions.py
sigconfluence/projects.py
sigconfluence/spaces.py
sigconfluence/users.py
sigconfluence/webhooks.py
confluence_cloud_python-1.1.2.dist-info/LICENCE
confluence_cloud_python-1.1.2.dist-info/METADATA
confluence_cloud_python-1.1.2.dist-info/WHEEL
confluence_cloud_python-1.1.2.dist-info/top_level.txt
confluence_cloud_python-1.1.2.dist-info/RECORD
