Metadata-Version: 2.1
Name: confluence-cloud-python
Version: 1.1.2
Summary: This package will provide access to Atlassian Confluence REST APIs
Home-page: https://github.com/erashwani
Author: Ashwani Sharma
Author-email: er.ashwani.it@gmail.com
License: UNKNOWN
Platform: UNKNOWN
Classifier: Programming Language :: Python :: 3
Classifier: License :: OSI Approved :: MIT License
Classifier: Operating System :: OS Independent
Requires-Python: >=3.6
